LICENSE
README.md
setup.cfg
setup.py
DataExploration/__init__.py
DataExploration/analysis.py
data_exploration_analysis.egg-info/PKG-INFO
data_exploration_analysis.egg-info/SOURCES.txt
data_exploration_analysis.egg-info/dependency_links.txt
data_exploration_analysis.egg-info/entry_points.txt
data_exploration_analysis.egg-info/requires.txt
data_exploration_analysis.egg-info/top_level.txt