Metadata-Version: 2.1
Name: data-exploration-analysis
Version: 3.1.2
Summary: Data exploration is the initial step in data analysis, where users explore a large data set in an unstructured way to uncover initial patterns, characteristics, and points of interest.
Home-page: https://github.com/christiangarcia0311/data-exploration-analysis
Author: Christian Garcia
Author-email: iyaniyan03112003@gmail.com
License: MIT
Classifier: Programming Language :: Python :: 3
Classifier: License :: OSI Approved :: MIT License
Classifier: Operating System :: OS Independent
Classifier: Topic :: Software Development :: Libraries :: Python Modules
License-File: LICENSE
Requires-Dist: matplotlib>=3.4.3
Requires-Dist: numpy>=1.21.0
Requires-Dist: pandas>=1.1.3
Requires-Dist: scipy>=1.7.0
